Networkx22ZhongwenWendang/README.md
Networkx22ZhongwenWendang/__init__.py
Networkx22ZhongwenWendang/__main__.py
Networkx22ZhongwenWendang/file.epub
Networkx22ZhongwenWendang/index.html
Networkx22ZhongwenWendang/css/__init__.py
Networkx22ZhongwenWendang/css/annotations.css
Networkx22ZhongwenWendang/css/main.css
Networkx22ZhongwenWendang/css/normalize.css
Networkx22ZhongwenWendang/css/popup.css
Networkx22ZhongwenWendang/font/__init__.py
Networkx22ZhongwenWendang/font/fontello.eot
Networkx22ZhongwenWendang/font/fontello.svg
Networkx22ZhongwenWendang/font/fontello.ttf
Networkx22ZhongwenWendang/font/fontello.woff
Networkx22ZhongwenWendang/img/__init__.py
Networkx22ZhongwenWendang/img/annotator-glyph-sprite.png
Networkx22ZhongwenWendang/img/annotator-icon-sprite.png
Networkx22ZhongwenWendang/img/apple-touch-icon.png
Networkx22ZhongwenWendang/img/cancelfullscreen.png
Networkx22ZhongwenWendang/img/close.png
Networkx22ZhongwenWendang/img/fullscreen.png
Networkx22ZhongwenWendang/img/loader.gif
Networkx22ZhongwenWendang/img/menu-icon.png
Networkx22ZhongwenWendang/img/save.png
Networkx22ZhongwenWendang/img/saved.png
Networkx22ZhongwenWendang/img/settings-s.png
Networkx22ZhongwenWendang/img/settings.png
Networkx22ZhongwenWendang/img/star.png
Networkx22ZhongwenWendang/js/__init__.py
Networkx22ZhongwenWendang/js/epub.js
Networkx22ZhongwenWendang/js/epub.min.js
Networkx22ZhongwenWendang/js/epub.min.map
Networkx22ZhongwenWendang/js/hooks.min.js
Networkx22ZhongwenWendang/js/hooks.min.map
Networkx22ZhongwenWendang/js/reader.js
Networkx22ZhongwenWendang/js/reader.js.map
Networkx22ZhongwenWendang/js/reader.min.js
Networkx22ZhongwenWendang/js/reader.min.map
Networkx22ZhongwenWendang/js/hooks/__init__.py
Networkx22ZhongwenWendang/js/hooks/extensions/__init__.py
Networkx22ZhongwenWendang/js/hooks/extensions/highlight.js
Networkx22ZhongwenWendang/js/libs/__init__.py
Networkx22ZhongwenWendang/js/libs/jquery.min.js
Networkx22ZhongwenWendang/js/libs/localforage.min.js
networkx_2_2_zhongwen_wendang-2024.3.4.0.dist-info/METADATA
networkx_2_2_zhongwen_wendang-2024.3.4.0.dist-info/WHEEL
networkx_2_2_zhongwen_wendang-2024.3.4.0.dist-info/entry_points.txt
networkx_2_2_zhongwen_wendang-2024.3.4.0.dist-info/top_level.txt
networkx_2_2_zhongwen_wendang-2024.3.4.0.dist-info/RECORD
